__init__.py
grayscale_to_rgb.py
grayscale_to_rgb/grayscale_to_rgb.py
grayscale_to_rgb-1.1.0.dist-info/METADATA
grayscale_to_rgb-1.1.0.dist-info/WHEEL
grayscale_to_rgb-1.1.0.dist-info/entry_points.txt
grayscale_to_rgb-1.1.0.dist-info/top_level.txt
grayscale_to_rgb-1.1.0.dist-info/RECORD
