Metadata-Version: 2.1
Name: grayscale-to-rgb
Version: 1.1.0
Summary: Mapping grayscale images to RGB
Home-page: https://gitlab.bfabric.org/jens/grayscale-to-rgb
Author: Elina Jansone
Author-email: hertaelina@gmail.com
License: MIT
Classifier: Development Status :: 3 - Alpha
Classifier: Intended Audience :: Science/Research
Classifier: License :: OSI Approved :: MIT License
Classifier: Operating System :: POSIX :: Linux
Classifier: Programming Language :: Python :: 3.10
Requires-Python: >=3.8
Requires-Dist: matplotlib (>=3.9.0)
Requires-Dist: argparse (>=1.4.0)
Provides-Extra: dev
Requires-Dist: twine (>=5.0.0) ; extra == 'dev'
